openfdem/__init__.py
openfdem/aggregate_storage.py
openfdem/complete_BD_thread_pool_generators.py
openfdem/complete_PLT_thread_pool_generators.py
openfdem/complete_UCS_thread_pool_generators.py
openfdem/direct_shear_thread_pool_generators.py
openfdem/extract_cell_thread_pool_generators.py
openfdem/extract_thread_pool_generators.py
openfdem/extract_threshold_thread_pool_generators.py
openfdem/formatting_codes.py
openfdem/model_reader.py
openfdem/openfdem.py
openfdem-4.1.dist-info/METADATA
openfdem-4.1.dist-info/WHEEL
openfdem-4.1.dist-info/top_level.txt
openfdem-4.1.dist-info/RECORD
